Workbook

Sheet Raw Data
A1: Order ID | B1: Order Date | C1: Ship Date | D1: Customer ID | E1: Customer Name | F1: Segment | G1: City | H1: State | I1: Region | J1: Product Category | K1: Sub Category | L1: Product Name | M1: Sales | N1: Quantity | O1: Discount | P1: Profit | Q1: Shipping Cost | R1: Payment Mode | S1: Order Priority
A2: ORD-7979 | B2: 31-Dec-2023 | C2: 07/01/2024 | D2: CUST-2075 | E2: Brandon Kelly | F2: Consumer | G2: Columbus | H2: Ohio | I2: Central | J2: technology | K2: Copiers | L2: Compact Copier | M2: 156.38 | N2: 2 | O2: 0.1 | P2: 31.11 | Q2: 48.55 | R2: Credit Card | S2: Low
A3: ORD-12072 | B3: 2026-04-18 | C3: 23-Apr-2026 | D3: CUST-2159 | E3: Kara Sandoval | F3: Corporate | G3: Miami | H3: Florida | I3: East | J3: furniture | K3: Chairs | L3: Ergonomic Office Chair | M3: 986.48 | N3: 8 | O3: 0.3 | P3: -102.9 | Q3: 30.77 | R3: DEBIT CARD | S3: Low
A4: ORD-6756 | B4: 15-Dec-2024 | C4: 12-22-2024 | D4: CUST-1337 | F4: Corporate | G4: Birmingham | H4: Alabama | I4: South | J4: Furniture | K4: Bookcases | L4: Oak Bookcase | M4: $1162.5 | N4: 3 | O4: 0.3 | P4: 66.88 | Q4: 44.8 | R4: upi | S4: High
A5: ORD-12634 | B5: 09-Dec-2023 | C5: 14/12/2023 | D5: CUST-1873 | E5: Amy Miller | F5: Home Office | G5: Albany | H5: New York | I5: East | J5: furniture | K5: Furnishings | L5: Desk Lamp | M5: 206.7 | N5: 3 | O5: 0.3 | P5: -4.43 | Q5: 37.99 | R5: UPI | S5: Critical
A6: ORD-14527 | B6: 30-Oct-2025 | C6: 10-31-2025 | D6: CUST-1855 | E6: Melissa Abbott | F6: CORPORATE | G6: Norfolk | H6: Virginia | I6: East | J6: Technology | K6: Accessories | L6: Laptop Stand | M6: 6846.35 | N6: 7 | O6: 0 | P6: 1973.68 | Q6: 57.6 | R6: Debit Card | S6: Low
A7: ORD-4886 | B7: 01-19-2026 | C7: 2026-01-22 | D7: CUST-1260 | E7: Katie Suarez | F7: Home Office | G7: Richmond | H7: Virginia | I7: East | J7: Office Supplies | K7: Art | L7: Sketch Pad | M7: 209.4 | N7: 12 | O7: 0 | Q7: 11.11 | R7: UPI | S7: Critical
A8: ORD-5268 | B8: 18-Sep-2023 | C8: 09-22-2023 | D8: CUST-1723 | E8: Todd Reynolds | F8: corporate | G8: Las Vegas | H8: Nevada | I8: West | J8: Furniture | K8: Furnishings | L8: Wall Clock | M8: 2705.92 | N8: 7 | O8: 0 | P8: 1214.63 | Q8: 58.08 | R8: debit card | S8: Medium
A9: ORD-12605 | B9: 18/08/2023 | C9: 08-20-2023 | D9: CUST-1028 | E9: Zachary Hicks | F9: Consumer | G9: San Antonio | H9: Texas | I9: Central | J9: Technology | K9: Machines | L9: Laser Printer | M9: 3137.44 | N9: 8 | O9: 0 | P9: 1380.59 | Q9: 7.77 | R9: CREDIT CARD | S9: Critical
A10: ORD-11390 | B10: 02/04/2026 | C10: 04-09-2026 | D10: CUST-1917 | E10: Christine Parker | F10: Corporate | G10: Worcester | H10: Massachusetts | I10: East | J10: OFFICE SUPPLIES | K10: Fasteners | L10: Push Pins | M10: 110.97 | N10: 9 | O10: 0 | P10: 19.56 | Q10: 8.14 | R10: Net Banking | S10: Low
A11: ORD-7268 | B11: 08/03/2026 | C11: 2026-03-12 | D11: CUST-1136 | E11: Robert Potter | F11: Consumer | G11: Lexington | H11: Kentucky | I11: South | J11: Office Supplies | K11: Storage | L11: Filing Cabinet | M11: 104.91 | N11: 3 | O11: 0.1 | P11: 27.54 | Q11: 4.63 | R11: upi | S11: Medium
A12: ORD-13637 | B12: 26/05/2025 | C12: 05-31-2025 | D12: CUST-2207 | E12: Dawn Rivera | F12: consumer | G12: springfield | H12: Illinois | I12: Central | J12: Office Supplies | K12: Art | L12: Colored Pencils | M12: 24.37 | N12: 1 | O12: 0.5 | P12: -5.2 | Q12: 37.44 | R12: UPI | S12: Low
A13: ORD-11892 | B13: 10-18-2023 | C13: 10-25-2023 | D13: CUST-1437 | E13: Christopher Guerra | F13: Consumer | G13: St. Louis | H13: Missouri | I13: Central | J13: furniture | K13: Furnishings | L13: Wall Clock | M13: 1051.92 | N13: 9 | O13: 0 | P13: 360.56 | Q13: 37.53 | R13: Cash on Delivery | S13: Medium
A14: ORD-7643 | B14: 12-27-2023 | C14: 28/12/2023 | D14: CUST-1112 | E14: Julia Torres | F14: Consumer | G14: San Francisco | H14: California | I14: West | J14: Office Supplies | K14: Labels | L14: Shipping Labels | M14: 145.8 | N14: 12 | O14: 0.1 | P14: 19.16 | Q14: 6.82 | R14: Debit Card | S14: Low
A15: ORD-14512 | B15: 05-02-2026 | C15: 05-07-2026 | D15: CUST-1382 | E15: Douglas Gregory | F15: HOME OFFICE | G15: Las Vegas | H15: Nevada | I15: West | J15: OFFICE SUPPLIES | K15: Storage | L15: Filing Cabinet | M15: 187.8 | N15: 6 | P15: 31.08 | Q15: 58.29 | R15: credit card | S15: High
A16: ORD-16774 | B16: 12-Mar-2024 | C16: 03-16-2024 | D16: CUST-1825 | E16: Monica Ellis | F16: consumer | G16: Chicago | H16: Illinois | I16: Central | J16: Furniture | K16: Chairs | L16: Ergonomic Office Chair | M16: 1286.73 | N16: 3 | O16: 0 | P16: 293.05 | Q16: 38.99 | R16: net banking | S16: Medium
A17: ORD-8475 | B17: 2025-03-28 | C17: 03-31-2025 | D17: CUST-1274 | E17: Joyce Bowen | F17: CONSUMER | G17: Eugene | H17: Oregon | I17: West | J17: Office Supplies | K17: Paper | L17: Copy Paper A4 | M17: 61.66 | N17: 2 | O17: 0.15 | P17: 5.17 | Q17: 43.94 | R17: CASH ON DELIVERY | S17: Critical
A18: ORD-15479 | B18: 29/10/2023 | C18: 11-01-2023 | D18: CUST-1133 | E18: Daniel Kennedy | F18: Corporate | G18: DULUTH | H18: Minnesota | I18: Central | J18: OFFICE SUPPLIES | K18: Art | L18: Marker Set | M18: 248.78 | N18: 7 | O18: 0.5 | P18: -29.59 | Q18: 56.2 | R18: Debit Card | S18: Medium
A19: ORD-9695 | B19: 12/10/2023 | C19: 2023-10-19 | D19: CUST-1606 | E19: Brian Martin | F19: CORPORATE | G19: Lexington | H19: Kentucky | I19: South | J19: Office Supplies | K19: Fasteners | L19: Push Pins | M19: 122.48 | N19: 8 | O19: 0 | P19: 46.05 | Q19: 4.49 | R19: Debit Card | S19: Low
A20: ORD-17400 | B20: 07/07/2024 | C20: 12-Jul-2024 | D20: CUST-2164 | E20: Mitchell Griffith | F20: corporate | G20: Newark | H20: New Jersey | I20: East | J20: OFFICE SUPPLIES | K20: Labels | L20: Address Labels | M20: 112.59 | N20: 9 | O20: 0.2 | P20: 8.53 | Q20: 3.12 | R20: Debit Card | S20: Low
A21: ORD-13169 | B21: 2025-10-01 | C21: 10-02-2025 | D21: CUST-1803 | E21: Rodney Williams | F21: CONSUMER | G21: LEXINGTON | H21: Kentucky | I21: South | J21: technology | K21: Phones | L21: Wireless Headset | M21: 3389.76 | N21: 11 | O21: 0 | P21: 743.62 | Q21: 10.44 | R21: UPI | S21: Low
A22: ORD-3764 | B22: 2024-07-20 | C22: 2024-07-23 | D22: CUST-1983 | E22: Sean Curtis | F22: consumer | G22: savannah | H22: Georgia | I22: South | J22: FURNITURE | K22: Furnishings | L22: Desk Lamp | M22: 83.05 | N22: 11 | O22: 0.5 | P22: -9.58 | Q22: 5.4 | R22: Net Banking | S22: High
A23: ORD-14619 | B23: 13-Jul-2026 | C23: 2026-07-20 | D23: CUST-2237 | E23: Nicole Richards | F23: Home Office | G23: Miami | H23: Florida | I23: East | J23: technology | K23: Machines | L23: Shredder | M23: 1946.34 | N23: 2 | O23: 0.3 | P23: -5.12 | Q23: 50.37 | R23: net banking | S23: Medium
A24: ORD-3648 | B24: 07-07-2025 | C24: 07-10-2025 | D24: CUST-1740 | E24: Eric Rush | F24: Corporate | G24: denver | H24: Colorado | I24: West | J24: technology | K24: Machines | L24: Label Maker | M24: 8933.16 | N24: 12 | O24: 0.5 | P24: -2067.26 | Q24: 15.82 | R24: CASH ON DELIVERY | S24: Low
A25: ORD-14198 | B25: 01-26-2026 | C25: 30-Jan-2026 | D25: CUST-2142 | E25: Joseph Haynes | F25: Home Office | G25: Boulder | H25: Colorado | I25: West | J25: Office Supplies | K25: Storage | L25: Drawer Organizer | M25: 180.18 | N25: 11 | O25: 0.3 | P25: -4.48 | Q25: 12.5 | R25: Credit Card | S25: Medium
A26: ORD-5050 | B26: 2023-12-24 | C26: 25/12/2023 | D26: CUST-2086 | E26: Mark Smith | F26: consumer | G26: Cleveland | H26: Ohio | I26: Central | J26: furniture | K26: Tables | L26: Round Conference Table | M26: 2560.77 | N26: 9 | O26: 0 | P26: 477.24 | Q26: 3.22 | R26: net banking | S26: Critical
A27: ORD-5598 | B27: 11-09-2023 | C27: 14-Nov-2023 | D27: CUST-1870 | E27: Kimberly Myers | F27: Home Office | G27: Charlotte | H27: North Carolina | I27: South | J27: Technology | K27: Phones | L27: Wireless Headset | M27: 2583.28 | N27: 4 | O27: 0.4 | P27: -642.87 | Q27: 39.79 | R27: UPI | S27: Medium
... A32: ORD-8173 | B32: 2026-07-02 | C32: 2026-07-03 | D32: CUST-1715 | E32: David Davenport | F32: Consumer | G32: Austin | H32: Texas | I32: Central | J32: furniture | K32: Tables | L32: Round Conference Table | M32: 1516.88 | N32: 8 | O32: 0 | P32: 576.56 | Q32: 23.67 | R32: NET BANKING | S32: Low
A33: ORD-7264 | B33: 08/12/2025 | C33: 2025-12-15 | D33: CUST-1972 | E33: Amanda Guzman | F33: consumer | G33: Savannah | H33: Georgia | I33: South | J33: Technology | K33: Machines | L33: Shredder | M33: 2208.4 | N33: 4 | O33: 0.4 | Q33: 6.7 | R33: Debit Card | S33: High
A34: ORD-17402 | B34: 04/01/2026 | C34: 06/01/2026 | D34: CUST-1112 | E34: Julia Torres | F34: CONSUMER | G34: LOUISVILLE | H34: Kentucky | I34: South | J34: Office Supplies | K34: Storage | L34: Filing Cabinet | M34: 47.08 | N34: 4 | O34: 0.15 | P34: 11.63 | Q34: 43.44 | R34: credit card | S34: Medium
A35: ORD-9978 | B35: 03-10-2026 | C35: 2026-03-11 | D35: CUST-1556 | E35: Kathryn Williams | F35: CORPORATE | G35: Jersey City | H35: New Jersey | I35: East | J35: TECHNOLOGY | K35: Phones | L35: Smartphone X200 | M35: 1969.28 | N35: 4 | O35: 0.15 | P35: 513.27 | Q35: 16.51 | R35: Debit Card | S35: Critical
A36: ORD-11153 | B36: 2025-11-02 | C36: 05/11/2025 | D36: CUST-1537 | E36: Bianca Wood | F36: consumer | G36: Columbus | H36: Ohio | I36: Central | J36: furniture | K36: Chairs | L36: Folding Chair | M36: 764.4 | N36: 7 | O36: 0.5 | P36: -60.56 | Q36: 41.82 | R36: debit card | S36: Low
A37: ORD-17764 | B37: 24/06/2026 | C37: 06-29-2026 | D37: CUST-2140 | E37: Patricia Ray | F37: corporate | G37: LEXINGTON | H37: Kentucky | I37: South | J37: OFFICE SUPPLIES | K37: Art | L37: Colored Pencils | M37: 69.0 | N37: 10 | O37: 0 | P37: 10.69 | Q37: 6.6 | R37: UPI | S37: Low
A38: ORD-5157 | B38: 2024-03-02 | C38: 09/03/2024 | D38: CUST-2351 | E38: Timothy Andrews | F38: Home Office | G38: TACOMA | H38: Washington | I38: West | J38: Furniture | K38: Chairs | L38: Ergonomic Office Chair | M38: 564.12 | N38: 3 | O38: 0.2 | P38: 60.1 | Q38: 20.39 | R38: CREDIT CARD | S38: High
A39: ORD-3693 | B39: 11-Aug-2025 | C39: 08-14-2025 | D39: CUST-1458 | E39: Aaron Miller | F39: Corporate | G39: Ann Arbor | H39: Michigan | I39: Central | J39: Technology | K39: Copiers | L39: Office Copier A3 | M39: 3102.93 | N39: 9 | O39: 0.15 | P39: 681.77 | Q39: 40.2 | R39: CASH ON DELIVERY | S39: Medium
A40: ORD-16483 | B40: 2024-09-30 | C40: 10-01-2024 | D40: CUST-1675 | E40: Larry Harris | F40: Consumer | G40: Savannah | H40: Georgia | I40: South | J40: technology | K40: Accessories | L40: Laptop Stand | M40: 1843.87 | N40: 7 | O40: 0.2 | P40: 149.62 | Q40: 8.26 | R40: credit card | S40: Medium
A41: ORD-3153 | B41: 01-Oct-2025 | C41: 03-Oct-2025 | D41: CUST-1298 | E41: Keith Jennings | F41: Home Office | G41: Worcester | H41: Massachusetts | I41: East | J41: office supplies | K41: Binders | L41: Heavy Duty Binder | M41: 48.7 | N41: 1 | O41: 0.15 | P41: 6.53 | Q41: 35.87 | R41: Debit Card | S41: Medium
A42: ORD-18178 | B42: 15-Apr-2024 | C42: 2024-04-20 | D42: CUST-1083 | E42: Paul Jones | F42: consumer | G42: kansas city | H42: Missouri | I42: Central | J42: Furniture | K42: Tables | L42: Adjustable Height Table | M42: 6182.82 | N42: 9 | O42: 0.3 | P42: -98.04 | Q42: 11.91 | R42: UPI | S42: Low
A43: ORD-3758 | B43: 07-24-2024 | C43: 2024-07-31 | D43: CUST-2132 | E43: Michael Brown | F43: consumer | G43: SEATTLE | H43: Washington | I43: West | J43: Technology | K43: Machines | L43: Label Maker | M43: 312.56 | N43: 4 | O43: 0 | P43: 105.73 | Q43: 49.35 | R43: debit card | S43: Critical
A44: ORD-8364 | B44: 26-Oct-2023 | C44: 28-Oct-2023 | D44: CUST-2061 | E44: Shannon Green | F44: HOME OFFICE | G44: Boulder | H44: Colorado | I44: West | J44: office supplies | K44: Paper | L44: Copy Paper A4 | M44: 168.14 | N44: 7 | O44: 0.3 | P44: -18.73 | Q44: 43.73 | R44: UPI | S44: Medium
A45: ORD-11963 | B45: 23-May-2026 | C45: 24/05/2026 | D45: CUST-1431 | E45: Jack White | F45: Corporate | G45: Norfolk | H45: Virginia | I45: East | J45: Furniture | K45: Furnishings | L45: Picture Frame | M45: 232.05 | N45: 1 | O45: 0 | P45: -832.64 | Q45: 53.83 | R45: UPI | S45: High
... A56: ORD-3540 | B56: 04-May-2026 | C56: 05/05/2026 | D56: CUST-1809 | E56: Heather Page | F56: Corporate | G56: Dallas | H56: Texas | I56: Central | J56: Technology | K56: Phones | L56: Office Desk Phone | M56: 2216.4 | N56: 12 | O56: 0 | P56: 445.17 | Q56: 44.05 | R56: Debit Card | S56: High
A57: ORD-8887 | B57: 20-May-2025 | C57: 2025-05-27 | D57: CUST-1843 | E57: Benjamin Reyes | F57: Consumer | H57: Minnesota | I57: Central | J57: Furniture | K57: Furnishings | L57: Wall Clock | M57: 1613.8 | N57: 5 | O57: 0 | P57: 665.56 | Q57: 26.45 | R57: Cash on Delivery | S57: Medium
A58: ORD-14306 | B58: 2024-04-28 | C58: 01-May-2024 | D58: CUST-1814 | E58: Scott Duke | F58: Corporate | G58: Memphis | H58: Tennessee | I58: South | J58: Furniture | K58: Bookcases | L58: Oak Bookcase | M58: 1335.24 | N58: 9 | P58: 161.92 | Q58: 37.57 | R58: DEBIT CARD
A59: ORD-17152 | B59: 12-Apr-2024 | C59: 16/04/2024 | D59: CUST-1625 | E59: Michael Miller | F59: CONSUMER | G59: SEATTLE | H59: Washington | I59: West | J59: office supplies | K59: Labels | L59: Address Labels | M59: 109.17 | N59: 3 | O59: 0.15 | P59: 7.94 | Q59: 25.99 | R59: UPI | S59: Critical
A60: ORD-8253 | B60: 2023-07-30 | C60: 2023-08-02 | D60: CUST-1197 | E60: Spencer Haynes | F60: CORPORATE | G60: Detroit | H60: Michigan | I60: Central | J60: Office Supplies | K60: Fasteners | L60: Paper Clips | M60: 99.12 | N60: 7 | O60: 0.5 | P60: -17.52 | Q60: 18.4 | R60: net banking | S60: Critical
A61: ORD-15866 | B61: 21-Nov-2024 | C61: 2024-11-22 | D61: CUST-1996 | E61: Edward Stanley | F61: Home Office | G61: Raleigh | H61: North Carolina | I61: South | J61: office supplies | K61: Paper | L61: Copy Paper A4 | M61: 168.85 | N61: 11 | O61: 0 | P61: 46.62 | Q61: 22.84 | R61: UPI | S61: High
A62: ORD-8927 | B62: 20/09/2023 | C62: 2023-09-21 | D62: CUST-2121 | E62: David Hinton | F62: Corporate | G62: eugene | H62: Oregon | I62: West | J62: Furniture | K62: Bookcases | L62: Corner Bookcase | M62: 184.4 | N62: 1 | O62: 0.2 | P62: 10.86 | Q62: 36.3 | R62: Net Banking | S62: Medium
A63: ORD-13137 | B63: 16-Apr-2024 | C63: 23/04/2024 | D63: CUST-1966 | E63: Marie Thompson | F63: CONSUMER | G63: Orlando | H63: Florida | I63: East | J63: Technology | K63: Machines | L63: Label Maker | M63: 351.0 | N63: 2 | O63: 0.2 | P63: 83.1 | Q63: 30.85 | R63: Credit Card | S63: High
A64: ORD-15137 | B64: 12-03-2023 | C64: 10/12/2023 | D64: CUST-1886 | E64: Jordan Williams | F64: Consumer | G64: Miami | H64: Florida | I64: East | J64: office supplies | K64: Art | L64: Marker Set | M64: 27.33 | N64: 3 | O64: 0 | P64: 8.32 | Q64: 6.31 | R64: CASH ON DELIVERY | S64: Critical
A65: ORD-16268 | B65: 02/05/2026 | C65: 05-09-2026 | D65: CUST-1058 | E65: Brent Jordan | F65: corporate | G65: Savannah | H65: Georgia | I65: South | J65: Office Supplies | K65: Fasteners | L65: Push Pins | M65: 44.91 | N65: 9 | O65: 0.3 | P65: -0.26 | Q65: 11.18 | R65: Credit Card | S65: Low
A66: ORD-10575 | B66: 20/03/2024 | C66: 2024-03-25 | D66: CUST-1351 | E66: Kimberly Nguyen | F66: Consumer | G66: Cleveland | H66: Ohio | I66: Central | J66: Technology | K66: Copiers | L66: Office Copier A3 | M66: 1682.6 | N66: 10 | O66: 0 | P66: 560.33 | Q66: 53.46 | R66: UPI | S66: Low
A67: ORD-3227 | B67: 2025-06-14 | C67: 18/06/2025 | D67: CUST-1236 | E67: Andrew Reynolds | F67: CORPORATE | G67: SEATTLE | H67: Washington | I67: West | J67: Technology | K67: Accessories | L67: USB Cable | M67: 2385.8 | N67: 5 | O67: 0.3 | P67: 20.8 | Q67: 53.9 | R67: Net Banking | S67: Critical
A68: ORD-8200 | B68: 2023-08-17 | C68: 08-20-2023 | D68: CUST-2004 | E68: Mary Miller | F68: Corporate | G68: Ann Arbor | H68: Michigan | I68: Central | J68: Furniture | K68: Tables | L68: Adjustable Height Table | M68: 211.76 | N68: 4 | O68: 0.4 | P68: -32.52 | Q68: 42.44 | R68: CREDIT CARD | S68: Low
A69: ORD-5328 | B69: 06/01/2025 | C69: 11/01/2025 | D69: CUST-2160 | E69: Ashley Malone | F69: Consumer | G69: Boulder | H69: Colorado | I69: West | J69: OFFICE SUPPLIES | K69: Storage | L69: Filing Cabinet | M69: 64.74 | N69: 3 | O69: 0.15 | P69: 11.88 | Q69: 27.86 | R69: UPI | S69: Critical
A70: ORD-5204 | B70: 07/08/2025 | C70: 2025-08-14 | D70: CUST-1980 | E70: James Oconnor | F70: Consumer | G70: Chicago | H70: Illinois | I70: Central | J70: Office Supplies | K70: Art | L70: Marker Set | M70: 212.76 | N70: 6 | O70: 0 | P70: 87.75 | Q70: 43.07 | R70: net banking | S70: Low
... A80: ORD-3317 | B80: 19-Apr-2024 | C80: 2024-04-21 | D80: CUST-1122 | E80: April Frost | F80: Corporate | G80: Columbus | H80: Ohio | I80: Central | J80: Office Supplies | K80: Binders | L80: Heavy Duty Binder | M80: 70.92 | N80: 4 | O80: 0.15 | P80: 11.14 | Q80: 38.53 | R80: UPI | S80: High
A81: ORD-16434 | B81: 23/03/2024 | C81: 26-Mar-2024 | D81: CUST-1829 | E81: Kenneth Knight | F81: Corporate | H81: Massachusetts | I81: East | J81: TECHNOLOGY | K81: Accessories | L81: Wireless Mouse | M81: 1281.7 | N81: 10 | O81: 0 | P81: 350.57 | Q81: 43.89 | R81: UPI | S81: High
A82: ORD-17192 | B82: 26/05/2025 | C82: 2025-05-31 | D82: CUST-1608 | E82: Rachel Bradley | F82: CORPORATE | G82: sacramento | H82: California | I82: West | J82: Office Supplies | K82: Art | L82: Marker Set | M82: 215.37 | N82: 9 | O82: 0 | P82: 72.98 | Q82: 19.32 | R82: CASH ON DELIVERY | S82: Critical
A83: ORD-12383 | B83: 2026-03-22 | C83: 25/03/2026 | D83: CUST-1601 | E83: Jennifer Simpson DVM | F83: Home Office | G83: Spokane | H83: Washington | I83: West | J83: Furniture | K83: Furnishings | L83: Picture Frame | M83: 3283.5 | N83: 11 | O83: 0.4 | P83: -113.69 | Q83: 43.17 | R83: cash on delivery | S83: Low
A84: ORD-16201 | B84: 03-25-2026 | C84: 2026-04-01 | D84: CUST-2382 | E84: John Austin | F84: CONSUMER | G84: Phoenix | H84: Arizona | I84: West | J84: Office Supplies | K84: Paper | L84: Copy Paper A4 | M84: 46.04 | N84: 1 | O84: 0.15 | P84: 3.97 | Q84: 28.87 | R84: NET BANKING | S84: Medium
A85: ORD-15287 | B85: 13-Mar-2026 | C85: 17/03/2026 | D85: CUST-1264 | E85: Yvonne Burns | F85: Home Office | G85: Spokane | H85: Washington | I85: West | J85: Office Supplies | K85: Art | L85: Sketch Pad | M85: 29.97 | N85: 9 | O85: 0.5 | P85: -10.04 | Q85: 17.73 | R85: Cash on Delivery | S85: High
A86: ORD-8782 | B86: 2025-12-22 | C86: 26/12/2025 | D86: CUST-1484 | E86: Jasmine Beltran | F86: corporate | G86: Memphis | H86: Tennessee | I86: South | J86: furniture | K86: Furnishings | L86: Picture Frame | M86: 1860.93 | N86: 9 | O86: 0 | P86: 744.47 | Q86: 4.05 | R86: Net Banking | S86: Medium
A87: ORD-13305 | B87: 01-19-2026 | C87: 23-Jan-2026 | D87: CUST-1276 | E87: Wayne Morgan | F87: Corporate | G87: Reno | H87: Nevada | I87: West | J87: FURNITURE | K87: Furnishings | L87: Desk Lamp | M87: 761.94 | N87: 6 | O87: 0 | P87: 140.34 | Q87: 39.27 | R87: NET BANKING | S87: Critical
A88: ORD-8497 | B88: 06-Apr-2024 | C88: 04-11-2024 | D88: CUST-2098 | E88: Stephen Cowan | F88: CONSUMER | G88: PORTLAND | H88: Oregon | I88: West | J88: Office Supplies | K88: Labels | L88: Shipping Labels | M88: 191.62 | N88: 11 | O88: 0.1 | P88: 64.67 | Q88: 15.03 | R88: Debit Card | S88: Critical
A89: ORD-7536 | B89: 09-09-2024 | C89: 14-Sep-2024 | D89: CUST-2217 | E89: Samantha Zavala MD | F89: HOME OFFICE | G89: St. Louis | H89: Missouri | I89: Central | J89: Technology | K89: Accessories | L89: USB Cable | M89: 4067.77 | N89: 7 | O89: 0.5 | P89: -451.66 | Q89: 11.2 | R89: debit card | S89: Low
A90: ORD-17720 | B90: 07-30-2024 | C90: 08-04-2024 | D90: CUST-1561 | E90: Kim Erickson | F90: Corporate | G90: Phoenix | H90: Arizona | I90: West | J90: office supplies | K90: Art | L90: Marker Set | M90: 51.7 | N90: 11 | O90: 0.3 | P90: 1.22 | Q90: 58.59 | R90: Debit Card
A91: ORD-9116 | B91: 02-26-2025 | C91: 01-Mar-2025 | D91: CUST-1933 | E91: Samantha Foster | F91: Corporate | G91: Duluth | H91: Minnesota | I91: Central | J91: furniture | K91: Bookcases | L91: 5-Shelf Bookcase | M91: 436.28 | N91: 2 | O91: 0.4 | P91: -58.81 | Q91: 32.37 | R91: Debit Card | S91: High
A92: ORD-16853 | B92: 2025-12-11 | C92: 12-14-2025 | D92: CUST-2220 | E92: Erica Moon | F92: consumer | G92: Duluth | H92: Minnesota | I92: Central | J92: OFFICE SUPPLIES | K92: Art | L92: Colored Pencils | M92: 265.95 | N92: 9 | O92: 0 | P92: 94.95 | Q92: 51.07 | R92: Debit Card | S92: High
A93: ORD-14538 | B93: 26/06/2026 | C93: 03/07/2026 | D93: CUST-1104 | E93: Richard Henson | F93: CORPORATE | G93: Louisville | H93: Kentucky | I93: South | J93: Office Supplies | K93: Labels | L93: Shipping Labels | M93: 156.0 | N93: 8 | O93: 0 | P93: 45.7 | Q93: 49.97 | R93: NET BANKING | S93: Low
A94: ORD-9156 | B94: 07-09-2025 | C94: 07-16-2025 | D94: CUST-1234 | E94: Michael Lyons | F94: Home Office | G94: Cleveland | H94: Ohio | I94: Central | J94: Furniture | K94: Chairs | L94: Folding Chair | M94: 1547.81 | N94: 11 | P94: -500.43 | Q94: 36.57 | R94: Debit Card | S94: Medium
A95: ORD-5131 | B95: 2026-01-01 | C95: 01-03-2026 | D95: CUST-1127 | E95: Jason Powell | F95: Corporate | G95: Baton Rouge | H95: Louisiana | I95: South | J95: FURNITURE | K95: Tables | L95: Glass Coffee Table | M95: 606.96 | N95: 8 | O95: 0 | P95: 153.46 | Q95: 21.45 | R95: UPI | S95: Medium
A96: ORD-17228 | B96: 2025-07-20 | C96: 24-Jul-2025 | D96: CUST-1150 | E96: David Wright | F96: Home Office | G96: ST. LOUIS | H96: Missouri | I96: Central | J96: OFFICE SUPPLIES | K96: Fasteners | L96: Push Pins | M96: 22.0 | N96: 2 | O96: 0 | P96: 7.76 | Q96: 7.66 | R96: debit card | S96: High
A97: ORD-10009 | B97: 26-Jul-2025 | C97: 31-Jul-2025 | D97: CUST-1742 | E97: George Ochoa | F97: CORPORATE | G97: philadelphia | H97: Pennsylvania | I97: East | J97: Technology | K97: Phones | L97: Wireless Headset | M97: 454.38 | N97: 3 | O97: 0.2 | P97: -4.97 | Q97: 34.75 | R97: Net Banking | S97: Critical
A98: ORD-7236 | B98: 04/07/2025 | C98: 2025-07-09 | D98: CUST-1960 | E98: Erica Johnson | F98: HOME OFFICE | G98: MIAMI | H98: Florida | I98: East | J98: OFFICE SUPPLIES | K98: Paper | L98: Copy Paper A4 | M98: 309.87 | N98: 11 | O98: 0.3 | P98: -0.4 | Q98: 3.3 | R98: Cash on Delivery | S98: Critical
A99: ORD-4209 | B99: 2025-04-02 | C99: 09/04/2025 | D99: CUST-1803 | E99: Rodney Williams | F99: Consumer | G99: Norfolk | H99: Virginia | I99: East | J99: technology | K99: Machines | L99: Label Maker | M99: 667.0 | N99: 10 | O99: 0.4 | P99: -99.63 | Q99: 4.9 | R99: Debit Card | S99: Low
A100: ORD-11683 | B100: 10/03/2026 | C100: 13/03/2026 | D100: CUST-1264 | E100: Yvonne Burns | F100: Consumer | G100: Reno | H100: Nevada | I100: West | J100: technology | K100: Accessories | L100: Wireless Mouse | M100: 271.06 | N100: 2 | O100: 0.2 | P100: 11.29 | Q100: 51.6 | R100: UPI | S100: Medium
A101: ORD-5124 | B101: 22-Oct-2024 | C101: 27/10/2024 | D101: CUST-2014 | E101: William Graham | F101: corporate | G101: Orlando | H101: Florida | I101: East | J101: OFFICE SUPPLIES | K101: Paper | L101: Legal Pad | M101: 136.51 | N101: 11 | O101: 0 | P101: 61.08 | Q101: 51.39 | R101: Debit Card | S101: Critical
A102: ORD-6420 | B102: 2025-09-14 | C102: 16/09/2025 | D102: CUST-2198 | E102: Emily Arnold | F102: CONSUMER | G102: Denver | H102: Colorado | I102: West | J102: Technology | K102: Phones | L102: Smartphone X200 | M102: 107.52 | N102: 12 | O102: 0.2 | P102: 25.44 | Q102: 47.42 | R102: UPI | S102: Critical
A103: ORD-16714 | B103: 10-03-2024 | C103: 10-10-2024 | D103: CUST-1559 | E103: Louis Martin | F103: CORPORATE | G103: Cleveland | H103: Ohio | I103: Central | J103: Technology | K103: Machines | L103: Label Maker | M103: 186.36 | N103: 1 | O103: 0.3 | P103: -8.1 | Q103: 42.29 | R103: net banking | S103: High
A104: ORD-4499 | B104: 2024-08-19 | C104: 08-24-2024 | D104: CUST-1028 | E104: Zachary Hicks | F104: Corporate | G104: Newark | H104: New Jersey | I104: East | J104: furniture | K104: Furnishings | L104: Picture Frame | M104: 651.42 | N104: 2 | O104: 0.15 | P104: 159.39 | Q104: 25.06 | R104: credit card | S104: Critical
A105: ORD-14559 | B105: 2023-08-03 | C105: 2023-08-05 | D105: CUST-1487 | E105: Samantha Gardner | F105: Home Office | G105: Springfield | H105: Illinois | I105: Central | J105: technology | K105: Accessories | L105: Wireless Mouse | M105: 863.16 | N105: 6 | O105: 0 | P105: 315.43 | Q105: 18.89 | R105: Cash on Delivery | S105: High
A106: ORD-10777 | B106: 09/01/2026 | C106: 2026-01-13 | D106: CUST-2292 | E106: Christine Lopez | F106: corporate | G106: Lexington | H106: Kentucky | I106: South | J106: FURNITURE | K106: Chairs | L106: Mesh Task Chair | M106: 1284.0 | N106: 8 | O106: 0 | P106: 504.07 | Q106: 4.31 | R106: UPI | S106: High
... A112: ORD-15982 | B112: 2025-08-16 | C112: 18-Aug-2025 | D112: CUST-2202 | E112: Kimberly Morrison | F112: Home Office | G112: philadelphia | H112: Pennsylvania | I112: East | J112: furniture | K112: Tables | L112: Round Conference Table | M112: 4492.08 | N112: 8 | O112: 0 | P112: 845.09 | Q112: 2.85 | R112: CASH ON DELIVERY | S112: High
A113: ORD-14165 | B113: 21/09/2025 | C113: 28-Sep-2025 | D113: CUST-1400 | E113: Robin Young | F113: Corporate | G113: Birmingham | H113: Alabama | I113: South | J113: Office Supplies | K113: Storage | L113: Storage Box | M113: 118.36 | N113: 11 | P113: 16.12 | Q113: 46.82 | R113: Credit Card | S113: High
A114: ORD-5822 | B114: 02-11-2024 | C114: 15/02/2024 | D114: CUST-2070 | E114: Susan Powers | F114: Corporate | G114: Springfield | H114: Illinois | I114: Central | J114: Furniture | K114: Bookcases | L114: Corner Bookcase | M114: 2798.3 | N114: 10 | O114: 0.5 | P114: -639.22 | Q114: 43.42 | R114: Net Banking | S114: Medium
A115: ORD-9747 | B115: 23-Aug-2023 | C115: 2023-08-28 | D115: CUST-1830 | E115: Mr. Michael Williams | F115: Consumer | G115: Baton Rouge | H115: Louisiana | I115: South | J115: TECHNOLOGY | K115: Phones | L115: Smartphone X200 | M115: 1202.94 | N115: 1 | O115: 0 | P115: 463.87 | Q115: 10 | R115: DEBIT CARD | S115: High
A116: ORD-17243 | B116: 11-06-2024 | C116: 09/11/2024 | D116: CUST-2080 | E116: Kathryn Dillon | F116: corporate | G116: San Francisco | H116: California | I116: West | J116: Technology | K116: Phones | L116: Smartphone X200 | M116: 2557.38 | N116: 6 | O116: 0 | P116: 708.71 | Q116: 44.17 | R116: UPI | S116: High
A117: ORD-10618 | B117: 2026-05-20 | C117: 05-25-2026 | D117: CUST-1639 | E117: Janet Kane DVM | F117: corporate | G117: Orlando | H117: Florida | I117: East | J117: technology | K117: Phones | L117: Wireless Headset | M117: 1607.05 | N117: 5 | O117: 0.4 | P117: 62.43 | Q117: 3.48 | R117: UPI | S117: Medium
A118: ORD-12000 | B118: 2024-11-25 | C118: 29/11/2024 | D118: CUST-2350 | E118: Destiny Obrien | F118: Corporate | G118: ATLANTA | H118: Georgia | I118: South | J118: Furniture | K118: Furnishings | L118: Wall Clock | M118: 1181.36 | N118: 4 | O118: 0.4 | P118: 44.71 | Q118: 57.44 | R118: Debit Card | S118: Medium
A119: ORD-7151 | B119: 19-May-2026 | C119: 23-May-2026 | D119: CUST-1449 | E119: Phillip Nelson | F119: consumer | G119: Lexington | H119: Kentucky | I119: South | J119: OFFICE SUPPLIES | K119: Art | L119: Marker Set | M119: 97.35 | N119: 3 | O119: 0.2 | P119: 21.87 | Q119: 38.43 | R119: Cash on Delivery | S119: Low
A120: ORD-3321 | B120: 2025-09-19 | C120: 2025-09-26 | D120: CUST-1480 | E120: Dawn Mullins | F120: consumer | G120: birmingham | H120: Alabama | I120: South | J120: Furniture | K120: Chairs | L120: Mesh Task Chair | M120: 2026.31 | N120: 11 | O120: 0.15 | P120: 36.21 | Q120: 42.64 | R120: Cash on Delivery | S120: Low
A121: ORD-7457 | B121: 07-01-2025 | C121: 05/07/2025 | D121: CUST-2349 | E121: Suzanne Bailey | F121: Home Office | G121: boulder | H121: Colorado | I121: West | J121: Technology | K121: Machines | L121: Laser Printer | M121: 5525.4 | N121: 12 | O121: 0.5 | P121: -1914 | Q121: 56.9 | R121: CREDIT CARD | S121: Low
A122: ORD-9560 | B122: 05-12-2024 | C122: 14-May-2024 | D122: CUST-1876 | E122: Michael Miles | F122: Home Office | G122: Montgomery | H122: Alabama | I122: South | J122: Furniture | K122: Chairs | L122: Mesh Task Chair | M122: 60.15 | N122: 1 | O122: 0.1 | P122: 19.2 | Q122: 22.87 | R122: UPI | S122: High
A123: ORD-5914 | B123: 2024-08-04 | C123: 08-05-2024 | D123: CUST-1542 | E123: Kenneth Edwards | F123: Home Office | G123: Louisville | H123: Kentucky | I123: South | J123: Furniture | K123: Furnishings | L123: Picture Frame | M123: 198.92 | N123: 4 | O123: 0.3 | P123: 8.36 | Q123: 29.4 | R123: Net Banking | S123: Critical
A124: ORD-7476 | B124: 07-Feb-2024 | C124: 2024-02-10 | D124: CUST-2180 | E124: Michelle Walls | F124: Home Office | G124: Columbus | H124: Ohio | I124: Central | J124: furniture | K124: Tables | L124: Round Conference Table | M124: 1680.32 | N124: 8 | O124: 0 | P124: 594.24 | Q124: 13.72 | R124: UPI
A125: ORD-11611 | B125: 2026-03-18 | C125: 25-Mar-2026 | D125: CUST-1435 | E125: Sophia Johnson | F125: Home Office | G125: Louisville | H125: Kentucky | I125: South | J125: TECHNOLOGY | K125: Copiers | L125: Compact Copier | M125: 6839.52 | N125: 12 | O125: 0.1 | P125: 1792.39 | Q125: 31.32 | R125: Debit Card | S125: Medium
A126: ORD-17325 | B126: 30/09/2024 | C126: 02/10/2024 | D126: CUST-1767 | E126: Haley Johnson | F126: corporate | G126: Louisville | H126: Kentucky | I126: South | J126: Technology | K126: Machines | L126: Label Maker | M126: 11085.72 | N126: 12 | O126: 0.1 | P126: 3168.58 | Q126: 26.46 | R126: UPI | S126: Low
A127: ORD-17930 | B127: 04-15-2025 | C127: 2025-04-20 | D127: CUST-1729 | E127: Derrick Anderson | F127: Corporate | G127: Kansas City | H127: Missouri | I127: Central | J127: furniture | K127: Chairs | L127: Ergonomic Office Chair | M127: 1166.4 | N127: 5 | O127: 0.3 | P127: 45.83 | Q127: 34.39 | R127: upi | S127: Medium
A128: ORD-14403 | B128: 2026-03-29 | C128: 2026-04-03 | D128: CUST-1538 | E128: Emma Owens | F128: Home Office | G128: Boston | H128: Massachusetts | I128: East | J128: Technology | K128: Copiers | L128: Compact Copier | M128: 2487.69 | N128: 9 | O128: 0 | P128: 834.38 | Q128: 51.21 | R128: Net Banking | S128: Low
...

Sheet Cleaning Formulas
A1: Order ID | B1: Order Date (Cleaned) | C1: Customer Name (Filled) | D1: City (Trimmed/Proper) | E1: Sales (Numeric) | F1: Discount (Filled) | G1: Profit (Rounded) | H1: Order Priority (Filled) | I1: Order Value Tier
A2: ='Raw Data'!A2 -> ORD-7979 | B2: =IFERROR(DATEVALUE('Raw Data'!B2),"Check Format") -> 45291 | C2: =IF('Raw Data'!E2="",IFERROR(INDEX('Raw Data'!$E$2:$E$501,MATCH('Raw Data'!D2,'Raw Data'!$D$2:$D$501,0)),"Unknown Customer"),'Raw Data'!E2) -> Brandon Kelly | D2: =PROPER(TRIM('Raw Data'!G2)) -> Columbus | E2: =ROUND(VALUE(SUBSTITUTE(TRIM('Raw Data'!M2),"$","")),2) -> 156.38 | F2: =IF('Raw Data'!O2="",0,'Raw Data'!O2) -> 0.1 | G2: =ROUND('Raw Data'!P2,2) -> 31.11 | H2: =IF('Raw Data'!S2="","Medium",'Raw Data'!S2) -> Low | I2: =IF(E2<100,"Small",IF(E2<500,"Medium",IF(E2<1500,"Large","Very Large"))) -> Medium
A3: ='Raw Data'!A3 -> ORD-12072 | B3: =IFERROR(DATEVALUE('Raw Data'!B3),"Check Format") -> 46130 | C3: =IF('Raw Data'!E3="",IFERROR(INDEX('Raw Data'!$E$2:$E$501,MATCH('Raw Data'!D3,'Raw Data'!$D$2:$D$501,0)),"Unknown Customer"),'Raw Data'!E3) -> Kara Sandoval | D3: =PROPER(TRIM('Raw Data'!G3)) -> Miami | E3: =ROUND(VALUE(SUBSTITUTE(TRIM('Raw Data'!M3),"$","")),2) -> 986.48 | F3: =IF('Raw Data'!O3="",0,'Raw Data'!O3) -> 0.3 | G3: =ROUND('Raw Data'!P3,2) -> -102.9 | H3: =IF('Raw Data'!S3="","Medium",'Raw Data'!S3) -> Low | I3: =IF(E3<100,"Small",IF(E3<500,"Medium",IF(E3<1500,"Large","Very Large"))) -> Large
A4: ='Raw Data'!A4 -> ORD-6756 | B4: =IFERROR(DATEVALUE('Raw Data'!B4),"Check Format") -> 45641 | C4: =IF('Raw Data'!E4="",IFERROR(INDEX('Raw Data'!$E$2:$E$501,MATCH('Raw Data'!D4,'Raw Data'!$D$2:$D$501,0)),"Unknown Customer"),'Raw Data'!E4) -> 0 | D4: =PROPER(TRIM('Raw Data'!G4)) -> Birmingham | E4: =ROUND(VALUE(SUBSTITUTE(TRIM('Raw Data'!M4),"$","")),2) -> 1162.5 | F4: =IF('Raw Data'!O4="",0,'Raw Data'!O4) -> 0.3 | G4: =ROUND('Raw Data'!P4,2) -> 66.88 | H4: =IF('Raw Data'!S4="","Medium",'Raw Data'!S4) -> High | I4: =IF(E4<100,"Small",IF(E4<500,"Medium",IF(E4<1500,"Large","Very Large"))) -> Large
A5: ='Raw Data'!A5 -> ORD-12634 | B5: =IFERROR(DATEVALUE('Raw Data'!B5),"Check Format") -> 45269 | C5: =IF('Raw Data'!E5="",IFERROR(INDEX('Raw Data'!$E$2:$E$501,MATCH('Raw Data'!D5,'Raw Data'!$D$2:$D$501,0)),"Unknown Customer"),'Raw Data'!E5) -> Amy Miller | D5: =PROPER(TRIM('Raw Data'!G5)) -> Albany | E5: =ROUND(VALUE(SUBSTITUTE(TRIM('Raw Data'!M5),"$","")),2) -> 206.7 | F5: =IF('Raw Data'!O5="",0,'Raw Data'!O5) -> 0.3 | G5: =ROUND('Raw Data'!P5,2) -> -4.43 | H5: =IF('Raw Data'!S5="","Medium",'Raw Data'!S5) -> Critical | I5: =IF(E5<100,"Small",IF(E5<500,"Medium",IF(E5<1500,"Large","Very Large"))) -> Medium
A6: ='Raw Data'!A6 -> ORD-14527 | B6: =IFERROR(DATEVALUE('Raw Data'!B6),"Check Format") -> 45960 | C6: =IF('Raw Data'!E6="",IFERROR(INDEX('Raw Data'!$E$2:$E$501,MATCH('Raw Data'!D6,'Raw Data'!$D$2:$D$501,0)),"Unknown Customer"),'Raw Data'!E6) -> Melissa Abbott | D6: =PROPER(TRIM('Raw Data'!G6)) -> Norfolk | E6: =ROUND(VALUE(SUBSTITUTE(TRIM('Raw Data'!M6),"$","")),2) -> 6846.35 | F6: =IF('Raw Data'!O6="",0,'Raw Data'!O6) -> 0 | G6: =ROUND('Raw Data'!P6,2) -> 1973.68 | H6: =IF('Raw Data'!S6="","Medium",'Raw Data'!S6) -> Low | I6: =IF(E6<100,"Small",IF(E6<500,"Medium",IF(E6<1500,"Large","Very Large"))) -> Very Large
A7: ='Raw Data'!A7 -> ORD-4886 | B7: =IFERROR(DATEVALUE('Raw Data'!B7),"Check Format") -> Check Format | C7: =IF('Raw Data'!E7="",IFERROR(INDEX('Raw Data'!$E$2:$E$501,MATCH('Raw Data'!D7,'Raw Data'!$D$2:$D$501,0)),"Unknown Customer"),'Raw Data'!E7) -> Katie Suarez | D7: =PROPER(TRIM('Raw Data'!G7)) -> Richmond | E7: =ROUND(VALUE(SUBSTITUTE(TRIM('Raw Data'!M7),"$","")),2) -> 209.4 | F7: =IF('Raw Data'!O7="",0,'Raw Data'!O7) -> 0 | G7: =ROUND('Raw Data'!P7,2) -> 0 | H7: =IF('Raw Data'!S7="","Medium",'Raw Data'!S7) -> Critical | I7: =IF(E7<100,"Small",IF(E7<500,"Medium",IF(E7<1500,"Large","Very Large"))) -> Medium
A8: ='Raw Data'!A8 -> ORD-5268 | B8: =IFERROR(DATEVALUE('Raw Data'!B8),"Check Format") -> 45187 | C8: =IF('Raw Data'!E8="",IFERROR(INDEX('Raw Data'!$E$2:$E$501,MATCH('Raw Data'!D8,'Raw Data'!$D$2:$D$501,0)),"Unknown Customer"),'Raw Data'!E8) -> Todd Reynolds | D8: =PROPER(TRIM('Raw Data'!G8)) -> Las Vegas | E8: =ROUND(VALUE(SUBSTITUTE(TRIM('Raw Data'!M8),"$","")),2) -> 2705.92 | F8: =IF('Raw Data'!O8="",0,'Raw Data'!O8) -> 0 | G8: =ROUND('Raw Data'!P8,2) -> 1214.63 | H8: =IF('Raw Data'!S8="","Medium",'Raw Data'!S8) -> Medium | I8: =IF(E8<100,"Small",IF(E8<500,"Medium",IF(E8<1500,"Large","Very Large"))) -> Very Large
A9: ='Raw Data'!A9 -> ORD-12605 | B9: =IFERROR(DATEVALUE('Raw Data'!B9),"Check Format") -> Check Format | C9: =IF('Raw Data'!E9="",IFERROR(INDEX('Raw Data'!$E$2:$E$501,MATCH('Raw Data'!D9,'Raw Data'!$D$2:$D$501,0)),"Unknown Customer"),'Raw Data'!E9) -> Zachary Hicks | D9: =PROPER(TRIM('Raw Data'!G9)) -> San Antonio | E9: =ROUND(VALUE(SUBSTITUTE(TRIM('Raw Data'!M9),"$","")),2) -> 3137.44 | F9: =IF('Raw Data'!O9="",0,'Raw Data'!O9) -> 0 | G9: =ROUND('Raw Data'!P9,2) -> 1380.59 | H9: =IF('Raw Data'!S9="","Medium",'Raw Data'!S9) -> Critical | I9: =IF(E9<100,"Small",IF(E9<500,"Medium",IF(E9<1500,"Large","Very Large"))) -> Very Large
A10: ='Raw Data'!A10 -> ORD-11390 | B10: =IFERROR(DATEVALUE('Raw Data'!B10),"Check Format") -> 46057 | C10: =IF('Raw Data'!E10="",IFERROR(INDEX('Raw Data'!$E$2:$E$501,MATCH('Raw Data'!D10,'Raw Data'!$D$2:$D$501,0)),"Unknown Customer"),'Raw Data'!E10) -> Christine Parker | D10: =PROPER(TRIM('Raw Data'!G10)) -> Worcester | E10: =ROUND(VALUE(SUBSTITUTE(TRIM('Raw Data'!M10),"$","")),2) -> 110.97 | F10: =IF('Raw Data'!O10="",0,'Raw Data'!O10) -> 0 | G10: =ROUND('Raw Data'!P10,2) -> 19.56 | H10: =IF('Raw Data'!S10="","Medium",'Raw Data'!S10) -> Low | I10: =IF(E10<100,"Small",IF(E10<500,"Medium",IF(E10<1500,"Large","Very Large"))) -> Medium
A11: ='Raw Data'!A11 -> ORD-7268 | B11: =IFERROR(DATEVALUE('Raw Data'!B11),"Check Format") -> 46237 | C11: =IF('Raw Data'!E11="",IFERROR(INDEX('Raw Data'!$E$2:$E$501,MATCH('Raw Data'!D11,'Raw Data'!$D$2:$D$501,0)),"Unknown Customer"),'Raw Data'!E11) -> Robert Potter | D11: =PROPER(TRIM('Raw Data'!G11)) -> Lexington | E11: =ROUND(VALUE(SUBSTITUTE(TRIM('Raw Data'!M11),"$","")),2) -> 104.91 | F11: =IF('Raw Data'!O11="",0,'Raw Data'!O11) -> 0.1 | G11: =ROUND('Raw Data'!P11,2) -> 27.54 | H11: =IF('Raw Data'!S11="","Medium",'Raw Data'!S11) -> Medium | I11: =IF(E11<100,"Small",IF(E11<500,"Medium",IF(E11<1500,"Large","Very Large"))) -> Medium
A12: ='Raw Data'!A12 -> ORD-13637 | B12: =IFERROR(DATEVALUE('Raw Data'!B12),"Check Format") -> Check Format | C12: =IF('Raw Data'!E12="",IFERROR(INDEX('Raw Data'!$E$2:$E$501,MATCH('Raw Data'!D12,'Raw Data'!$D$2:$D$501,0)),"Unknown Customer"),'Raw Data'!E12) -> Dawn Rivera | D12: =PROPER(TRIM('Raw Data'!G12)) -> Springfield | E12: =ROUND(VALUE(SUBSTITUTE(TRIM('Raw Data'!M12),"$","")),2) -> 24.37 | F12: =IF('Raw Data'!O12="",0,'Raw Data'!O12) -> 0.5 | G12: =ROUND('Raw Data'!P12,2) -> -5.2 | H12: =IF('Raw Data'!S12="","Medium",'Raw Data'!S12) -> Low | I12: =IF(E12<100,"Small",IF(E12<500,"Medium",IF(E12<1500,"Large","Very Large"))) -> Small
A13: ='Raw Data'!A13 -> ORD-11892 | B13: =IFERROR(DATEVALUE('Raw Data'!B13),"Check Format") -> Check Format | C13: =IF('Raw Data'!E13="",IFERROR(INDEX('Raw Data'!$E$2:$E$501,MATCH('Raw Data'!D13,'Raw Data'!$D$2:$D$501,0)),"Unknown Customer"),'Raw Data'!E13) -> Christopher Guerra | D13: =PROPER(TRIM('Raw Data'!G13)) -> St. Louis | E13: =ROUND(VALUE(SUBSTITUTE(TRIM('Raw Data'!M13),"$","")),2) -> 1051.92 | F13: =IF('Raw Data'!O13="",0,'Raw Data'!O13) -> 0 | G13: =ROUND('Raw Data'!P13,2) -> 360.56 | H13: =IF('Raw Data'!S13="","Medium",'Raw Data'!S13) -> Medium | I13: =IF(E13<100,"Small",IF(E13<500,"Medium",IF(E13<1500,"Large","Very Large"))) -> Large
... A501: ='Raw Data'!A501 -> ORD-14622 | B501: =IFERROR(DATEVALUE('Raw Data'!B501),"Check Format") -> Check Format | C501: =IF('Raw Data'!E501="",IFERROR(INDEX('Raw Data'!$E$2:$E$501,MATCH('Raw Data'!D501,'Raw Data'!$D$2:$D$501,0)),"Unknown Customer"),'Raw Data'!E501) -> Eugene Baldwin | D501: =PROPER(TRIM('Raw Data'!G501)) -> Norfolk | E501: =ROUND(VALUE(SUBSTITUTE(TRIM('Raw Data'!M501),"$","")),2) -> 8561.6 | F501: =IF('Raw Data'!O501="",0,'Raw Data'!O501) -> 0 | G501: =ROUND('Raw Data'!P501,2) -> 1492.65 | H501: =IF('Raw Data'!S501="","Medium",'Raw Data'!S501) -> Critical | I501: =IF(E501<100,"Small",IF(E501<500,"Medium",IF(E501<1500,"Large","Very Large"))) -> Very Large

Sheet Summary (SUMIF-COUNTIF)
A1: Order Priority | B1: Order Count (COUNTIF) | C1: Total Profit (SUMIF)
A2: Low | B2: =COUNTIF('Cleaning Formulas'!H2:H501,A2) -> 131 | C2: =ROUND(SUMIF('Cleaning Formulas'!H2:H501,A2,'Cleaning Formulas'!G2:G501),2) -> 21228.71
A3: Medium | B3: =COUNTIF('Cleaning Formulas'!H2:H501,A3) -> 136 | C3: =ROUND(SUMIF('Cleaning Formulas'!H2:H501,A3,'Cleaning Formulas'!G2:G501),2) -> 21468.61
A4: High | B4: =COUNTIF('Cleaning Formulas'!H2:H501,A4) -> 111 | C4: =ROUND(SUMIF('Cleaning Formulas'!H2:H501,A4,'Cleaning Formulas'!G2:G501),2) -> 15522.01
A5: Critical | B5: =COUNTIF('Cleaning Formulas'!H2:H501,A5) -> 122 | C5: =ROUND(SUMIF('Cleaning Formulas'!H2:H501,A5,'Cleaning Formulas'!G2:G501),2) -> 24027.72
A8: Order Value Tier | B8: Count | C8: Avg Profit (SUMIFS/COUNTIFS)
A9: Small | B9: =COUNTIF('Cleaning Formulas'!I2:I501,A9) -> 67 | C9: =IFERROR(ROUND(SUMIFS('Cleaning Formulas'!G2:G501,'Cleaning Formulas'!I2:I501,A9)/B9,2),0) -> 4.19
A10: Medium | B10: =COUNTIF('Cleaning Formulas'!I2:I501,A10) -> 157 | C10: =IFERROR(ROUND(SUMIFS('Cleaning Formulas'!G2:G501,'Cleaning Formulas'!I2:I501,A10)/B10,2),0) -> 30.67
A11: Large | B11: =COUNTIF('Cleaning Formulas'!I2:I501,A11) -> 102 | C11: =IFERROR(ROUND(SUMIFS('Cleaning Formulas'!G2:G501,'Cleaning Formulas'!I2:I501,A11)/B11,2),0) -> 91.16
A12: Very Large | B12: =COUNTIF('Cleaning Formulas'!I2:I501,A12) -> 174 | C12: =IFERROR(ROUND(SUMIFS('Cleaning Formulas'!G2:G501,'Cleaning Formulas'!I2:I501,A12)/B12,2),0) -> 389.96
A15: Note: Sample of 500 raw rows shown for formula demonstration. Full 15,200-row cleaned dataset is produced by Python/data_cleaning.py and stored in Dataset/Cleaned_Data.xlsx.
